vimura_server/__init__.py
vimura_server/pythonstartup.py
vimura_server/vimura.py
vimura_server-1.3.dist-info/LICENSE
vimura_server-1.3.dist-info/METADATA
vimura_server-1.3.dist-info/WHEEL
vimura_server-1.3.dist-info/top_level.txt
vimura_server-1.3.dist-info/RECORD
