Metadata-Version: 2.1
Name: vimura-server
Version: 1.3
Summary: Alternative server for Emacs pdf-tools
Home-page: https://github.com/dalanicolai/pdf-tools/tree/pymupdf-tq
Author: Daniel Nicolai
Author-email: dalanicolai@gmail.com
License: UNKNOWN
Project-URL: Bug Tracker, https://github.com/dalanicolai/pdf-tools/issues
Platform: UNKNOWN
Classifier: Programming Language :: Python :: 3
Classifier: License :: OSI Approved :: GNU General Public License v3 (GPLv3)
Classifier: Operating System :: OS Independent
Requires-Python: >=3.6
License-File: LICENSE
Requires-Dist: PyMuPDF
Requires-Dist: Pillow
Requires-Dist: pytz
